[{"ID":"ث1","title":"مشاهير من تاريخنا للناشئة","subtitle":"ج1-ج12","author":"زكريا كايا","publisher":"الراتب الجامعية","publishYear":"0","country":"لبنان","pages":"0"},{"ID":"ث2","title":"سيدة العالم القديم","author":"زاهي حواس","publisher":"الشروق","publishYear":"2001","country":"القاهرة","pages":"0"},{"ID":"ث3","title":"المشهد السردي في القرآن الكريم","subtitle":"قراءة في قصة سيدنا يوسف عليه السلام","author":"حبيب مونسي","publisher":"دار المعرفة","publishYear":"2010","country":"الجزائر","pages":"0"},{"ID":"ث4","title":"هذا هو الإسلام","author":"محمد الصالح الصديق","publisher":"ديوان المطبوعات الجامعية","publishYear":"2003","country":"الجزائر","pages":"0"},{"ID":"ث5","title":"الحدث في تاريخ الجزائر المعاصر (1945-1962)","author":"حربي محمد","publisher":"منشورات دار الابحاث","publishYear":"0","country":"الجزائر","pages":"0"},{"ID":"ث6","title":"الإحصاء التطبيقي مع تمارين ومسائل محلولة","author":"جلاطو جيلالي","publisher":"دار الخلدونية","publishYear":"2009","country":"الجزائر","pages":"0"},{"ID":"ث7","title":"جدل الديني و السياسي في اليهودية و الإسلام بين المقدس و المدنس","author":"موسى معيرش","publisher":"دار بهاء الدين","publishYear":"2010","country":"الجزائر","pages":"0"},{"ID":"ث8","title":"بيدرو و كاترينا الأوراسية","author":"محمد الطاهر سحري","publisher":"د.ن","publishYear":"2008","country":"الجزائر","pages":"0"},{"ID":"ث9","title":"ابن المقفع و كتابه كليلة و دمنة","subtitle":"دراسة تحليلية","author":"ندية حفيز","publisher":"دار هومة","publishYear":"2005","country":"الجزائر","pages":"0"},{"ID":"ث10","title":"الوافي في أحكام الزكاة","subtitle":"دراسة مقارنة بين المذاهب وآراء العلماء","author":"أحمد إدريس عبدو","publisher":"الهدى","publishYear":"2006","country":"الجزائر","pages":"0"},{"ID":"ث11","title":"مناهج المفسرين في العصر الحديث","subtitle":"بين النظرية والتطبيق","author":"منصور كافي","publisher":"العلوم","publishYear":"2006","country":"الجزائر","pages":"0"},{"ID":"ث12","title":"طب الاعشاب والنباتات الطبية بين الحقائق والموروث الشعبي","author":"ماهر حسن محمود","publisher":"دار الوفاء لدنيا","publishYear":"2010","country":"الاسكندرية","pages":"0"},{"ID":"ث13","title":"الذيل التام على دول الاسلام للذهبي الجزء 1 . 2 . 3","author":"الامام الحافظ المؤرخ شمس الدين ","publisher":"مكتبة العربية","publishYear":"1996","country":"الكويت","pages":"0"},{"ID":"ث14","title":"اليهود في القرآن","subtitle":"تحليل علمي لنصوص القرآن في اليهود على ضوء الأحداث الحاضرة مع قصص أنبياء الله ابر","author":"عفيف عبد الفتاح طباره","publisher":"العلم للملايين","publishYear":"2004","country":"لبنان","pages":"0"},{"ID":"ث15","title":"تاريخ الطب والأطباء المسلمين","subtitle":"موسوعة للطب في عصر ازدهار حضارة الإسلام قصص العباقرة من أطباء المسلمين ومنجزاتهم","author":"المازني إسلام","publisher":"دار العراب","publishYear":"2010","country":"دمشق","pages":"0"},{"ID":"ث16","title":"خديعة مخطوطات البحر الميت","author":"بيجنت مايكل","publisher":"صفحات للدراسات والنشر","publishYear":"2010","country":"سورية","pages":"0"},{"ID":"ث17","title":"دراسات في الفن الاسلامي","author":"هادي بلقيس محسن","publisher":"دار دجلة","publishYear":"2010","country":"عمان","pages":"0"},{"ID":"ث18","title":"منهجية ابن خلدون في تدوين السيرة النبوية وتفسيرها","author":"عبد القادر سالمة محمود محمد","publisher":"دار الكتب العلمية","publishYear":"2010","country":"بيروت","pages":"0"},{"ID":"ث19","title":"التشريعات السياحية والفندقية","author":"أمجد حسن العزام","publisher":"الوراق","publishYear":"2008","country":"الأردن","pages":"0"},{"ID":"ث20","title":"مشكلات حضانة الأطفال في زواج الأجانب","author":"صلاح الدين جمال الدين","publisher":"الكتب القانونية","publishYear":"2005","country":"القاهرة","pages":"0"},{"ID":"ث21","title":"في علم الكلام","subtitle":"دراسة فلسفية لآراء الفرق الإسلامية في أصول الدين 1/المعتزلة 2/الأشاعرة","author":"أحمد محمود صبحي","publisher":"الثقافة الجامعية","publishYear":"1992","country":"الاسكندرية","pages":"0"},{"ID":"ث22","title":"أكبر الاكتشافات والاختراعات في تاريخ البشرية","author":"عزيزي عبد السلام","publisher":"مدني","publishYear":"0","country":"الجزائر","pages":"0"},{"ID":"ث23","title":"البني والدلالات في لغة القصص القرآني","subtitle":"دراسة فنية","author":"عماد عبد يحي","publisher":"دجلة","publishYear":"2009","country":"الأردن","pages":"0"},{"ID":"ث24","title":"الزوائد في صيغ العربية","author":"زين كامل الخويسكي","publisher":"المعرفة الجامعية","publishYear":"2008","country":"الاسكندرية","pages":"0"},{"ID":"ث25","title":"مأمون","subtitle":"مشروع حلم","author":"شكري خوجة","publisher":"anep","publishYear":"2010","country":"الرويبة","pages":"0"},{"ID":"ث26","title":"دعاء الحمام","subtitle":"مسرح","author":"زهور ونيسي","publisher":"anep","publishYear":"2010","country":"الجزائر","pages":"0"},{"ID":"ث27","title":"المدخل لدراسة البلاغة العربية","author":"محمد أبو الشوارب","publisher":"الوفاء","publishYear":"2007","country":"الإسكندرية","pages":"0"},{"ID":"ث28","title":"الوظيفة وموتها في العرض المسرحي","author":"يحي البشتاوي","publisher":"الأمانة العامة","publishYear":"2007","country":"الأردن","pages":"0"},{"ID":"ث29","title":"اكتساب الملكية بوضع اليد في العلاقة بين الدولة والأفراد","subtitle":"دراسة نظرية وعلمية","author":"جابر محجوب علي","publisher":"مجلس النشر العلمي","publishYear":"2005","country":"الكويت","pages":"0"},{"ID":"ث30","title":"جماليات الصورة","author":"غادة الامام","publisher":"التنوير","publishYear":"2010","country":"لبنان","pages":"0"},{"ID":"ث31","title":"سيكولوجيا الأدب","subtitle":"الماهية والإتجاهات","author":"سعاد جبر سعيد","publisher":"عالم الكتب الحديث","publishYear":"2008","country":"الأردن","pages":"0"},{"ID":"ث32","title":"من أعلام الفن التشكيلي في الخليج العربي","author":"محمد حسين جودي","publisher":"صفاء","publishYear":"2000","country":"الأردن","pages":"0"},{"ID":"ث33","title":"وحي وعبر","author":"محمد صالح الصديق","publisher":"د م ج","publishYear":"2011","country":"الجزائر","pages":"0"},{"ID":"ث34","title":"منطق السرد في سورة الكهف","author":"بوقرومة حكيمة","publisher":"د م ج","publishYear":"2011","country":"الجزائر","pages":"0"},{"ID":"ث35","title":"النبوة بين فخر الدين الرازي وابن عربي","subtitle":"دراسة مقارنة","author":"محمد عبد الحميد محمد","publisher":"دار الوفاء","publishYear":"0","country":"الاسكندرية","pages":"0"},{"ID":"ث36","title":"لغة القرآن والحديث","author":"عبد الغفار حامد هلال","publisher":"العلوم","publishYear":"2007","country":"القاهرة","pages":"0"},{"ID":"ث37","title":"سلسلة أعمال القلوب","author":"محمد صالح المنجد","publisher":"الفجر","publishYear":"2005","country":"القاهرة","pages":"0"},{"ID":"ث38","title":"الهندسة الوراثية في القرآن","subtitle":"وأسرار الروح وخلق الإنسان","author":"محمد محمود عبد الله","publisher":"مكتبة الإيمان","publishYear":"2003","country":"القاهرة","pages":"0"},{"ID":"ث39","title":"المحكمة الإلهية","author":"مصطفى مراد","publisher":"الفجر","publishYear":"2004","country":"القاهرة","pages":"0"},{"ID":"ث40","title":"التحفة السنية بشرح المقدمة الأجرومية","author":"محمد محي الدين عبد الحميد","publisher":"مدني","publishYear":"2003","country":"الجزائر","pages":"0"},{"ID":"ث41","title":"عقد الزواج","subtitle":"دراسة مقارنة","author":"عيسى حداد","publisher":"جامعة باجي مختار","publishYear":"2006","country":"الجزائر","pages":"0"},{"ID":"ث42","title":"أدلة الأحكام في عهد النبوة وعصر الخلفاء","author":"الشحات السيد زغلول","publisher":"المعرفة الجامعية","publishYear":"2003","country":"الاسكندرية","pages":"0"},{"ID":"ث43","title":"سلسلة فقه العبادات للمسلمين والمسلمات-الطهارة-","author":"محمد حريزي","publisher":"مدني","publishYear":"2002","country":"الجزائر","pages":"0"},{"ID":"ث44","title":"رسالة في القواعد الفقهية","author":"عبد الرحمن بن ناصر السعيدي","publisher":"مدني","publishYear":"1994","country":"الجزائر","pages":"0"},{"ID":"ث45","title":"الحياة بعد الموت","subtitle":"الروح بين العلم والعقيدة","author":"حسين نجيب محمد","publisher":"الهدى","publishYear":"2005","country":"لبنان","pages":"0"},{"ID":"ث46","title":"الموت في المأثورات الشعبية","author":"سميح عبد الغفار شعلان","publisher":"عين للدراسات","publishYear":"2000","country":"د.م","pages":"0"},{"ID":"ث47","title":"عالمية الإسلام وأخلاقيات رسوله","author":"محمد الصالح الصديق","publisher":"ديوان المطبوعات الجامعية","publishYear":"2008","country":"الجزائر","pages":"0"},{"ID":"ث48","title":"الاستغناء في الفرق والاستثناء","author":"محمد بن أبي سليمان البكري","publisher":"معهد البحوث العلمية","publishYear":"1988","country":"مكة المكرمة","pages":"0"},{"ID":"ث49","title":"غذاء الجسد والروح","subtitle":"شفاء الانسان وتفجير طاقاته الكامنة","author":"إبراهيم حسين سرور","publisher":"الهادي","publishYear":"2006","country":"لبنان","pages":"0"},{"ID":"ث50","title":"بيضة الأنوار في سيرة النبي المختار (ص)","author":"محمد بن مصطفى ","publisher":"ديوان المطبوعات الجامعية","publishYear":"2006","country":"الجزائر","pages":"0"},{"ID":"ث51","title":"نهج الصداقة وآدابها","author":"اسماعيل جوهري","publisher":"الهادي","publishYear":"2006","country":"لبنان","pages":"0"},{"ID":"ث52","title":"عبقرية عمر بن الخطاب رضي الله عنه","author":"عباس محمود العقاد","publisher":"مدني","publishYear":"2003","country":"الجزائر","pages":"0"},{"ID":"ث53","title":"موسوعة الصحابيات","subtitle":"التربية بالقدوة","author":"شاهر ذيب أبو شريخ","publisher":"صفاء","publishYear":"2003","country":"عمان","pages":"0"},{"ID":"ث54","title":"في مقارنة المعتقدات والأديان وفق منهج القرآن","subtitle":"دراسة أكاديمية","author":"سعدون محمود الساموك","publisher":"وائل","publishYear":"2006","country":"الأردن","pages":"0"},{"ID":"ث55","title":"المستقبل لهذا الدين","author":"سيد قطب","publisher":"مدني","publishYear":"2003","country":"الجزائر","pages":"0"},{"ID":"ث56","title":"المرأة في الإسلام وفي الفكر الغربي","author":"فؤاد حيدر","publisher":"الفكر العربي","publishYear":"1992","country":"لبنان","pages":"0"},{"ID":"ث57","title":"إنعقاد البيع بوسائل الإتصال الحديثة","subtitle":"دراسة فقهية مقارنة","author":"إبراهيم رفعت الجمال","publisher":"الفكر الجامعي","publishYear":"2006","country":"الاسكندرية","pages":"0"},{"ID":"ث58","title":"مع الرسول في بالغته وهجرته وإسرائه ومعراجه","author":"محمد الصالح الصديق","publisher":"opu","publishYear":"1989","country":"الجزائر","pages":"0"},{"ID":"ث59","title":"الحسين بن علي","subtitle":"سلسلة عظماء التاريخ","author":"زاهية الدجاني","publisher":"الكتاب العربي","publishYear":"2003","country":"لبنان","pages":"0"},{"ID":"ث60","title":"منهجية تدريس المواد الشرعية","author":"علي أحمد مدكور","publisher":"دار الفكر العربي","publishYear":"1999","country":"القاهرة","pages":"0"},{"ID":"ث61","title":"السببية عند القاضي عبد الجبار","author":"ابراهيم تركي","publisher":"الوفاء","publishYear":"2004","country":"الاسكندرية","pages":"0"},{"ID":"ث62","title":"شرح العقيدة الطحاوية","author":"العلامة صدر الدين علي بن علي","publisher":"ابن حزم","publishYear":"2003","country":"لبنان","pages":"0"},{"ID":"ث63","title":"التذكرة بأحوال الموتى والآخرة","author":"أبو عبد الله القرطبي","publisher":"مدني","publishYear":"2003","country":"الجزائر","pages":"0"},{"ID":"ث64","title":"أخطاؤنا في العبادات والمعاملات","author":"مصطفى مراد","publisher":"الفجر","publishYear":"2005","country":"القاهرة","pages":"0"},{"ID":"ث65","title":"عجائب الله في السماء والأرض","author":"محمد حريزي","publisher":"مدني","publishYear":"2003","country":"الجزائر","pages":"0"},{"ID":"ث66","title":"الشيخ الرزقي الشرقاوي","subtitle":"حيات و آثار،شهادات و مواقف ","author":"محمد الصالح الصديق","publisher":"دار الأمة","publishYear":"1998","country":"الجزائر","pages":"0"},{"ID":"ث67","title":"تلبيس إبليس","author":"أبي الفرج عبد الرحمن بن الجوزي","publisher":"دار الكتب العلمية","publishYear":"2002","country":"لبنان","pages":"0"},{"ID":"ث68","title":"إعجاز القرآن","subtitle":"للإمام القاضي أبي بكر محمد بن الطيب","author":"محمد عبد المنعم خفاجي","publisher":"الجيل","publishYear":"2005","country":"لبنان","pages":"0"},{"ID":"ث69","title":"حاشية العدوي","subtitle":"العلامة المحقق على بن أحمد بن مكرم","author":"محمد عبد الله شاهين","publisher":"الكتب العلمية","publishYear":"1998","country":"لبنان","pages":"0"},{"ID":"ث70","title":"الفواكه الدواني","subtitle":"على رسالة إبن أبي زيد الميترواني","author":"احمد بن غيثم بن سالم بن مهنا","publisher":"الكتب العلمية","publishYear":"1998","country":"لبنان","pages":"0"},{"ID":"ث71","title":"مروج الذهب ومعادن الجوهر","author":"مفيد محمد قميحة","publisher":"الكتب العلمية","publishYear":"0","country":"لبنان","pages":"0"},{"ID":"ث72","title":"أكثر من 1500 جواب للمرأة","author":"أحمد بن شعبان بن أحمد","publisher":"مكتبة الصفا","publishYear":"2006","country":"القاهرة","pages":"0"},{"ID":"ث73","title":"مفاتيح للفقه في الدين","author":"مصطفى بن العدوي","publisher":"مدني","publishYear":"2001","country":"الجزائر","pages":"0"},{"ID":"ث74","title":"مدارج السالكين بين منازل \"إياك نعبد وإياك نستعين\"","author":"شمس الدين محمد بن أبي بكر","publisher":"دار الكتاب العربي","publishYear":"2004","country":"لبنان","pages":"0"},{"ID":"ث75","title":"المدخل في الفقه الإسلامي","subtitle":"تعريفه وتاريخه ومذاهبه","author":"محمد مصطفى شلبي","publisher":"الدار الجامعية","publishYear":"1985","country":"لبنان","pages":"0"},{"ID":"ث76","title":"أحكام المولود في السنة المطهرة","author":"سالم علي راشد الشبلي","publisher":"مدني","publishYear":"1998","country":"الجزائر","pages":"0"},{"ID":"ث77","title":"رمز الصحة في طب النبي والأئمة","author":"السيد محمود الموسوي الدهسر خي الأصفهاني","publisher":"دار الهدى","publishYear":"2003","country":"لبنان","pages":"0"},{"ID":"ث78","title":"مباحث في علم الكلام والفلسفة","author":"الشابي علي","publisher":"دار المدار الاسلامي","publishYear":"2001","country":"ليبيا","pages":"0"},{"ID":"ث79","title":"الإسلام في قفص الاتهام","author":"شوقي أبو خليل","publisher":"دار الفكر","publishYear":"1992","country":"الجزائر","pages":"0"},{"ID":"ث80","title":"الله يتجلى في عصر العلم","author":"مجموعة من العلماء","publisher":"مدني","publishYear":"2002","country":"الجزائر","pages":"0"},{"ID":"ث81","title":"مهارات تدريس القرآن الكريم","author":"ماجد زكي الجلاد","publisher":"المسيرة","publishYear":"2007","country":"عمان","pages":"0"},{"ID":"ث82","title":"المقصد الأسنى شرح معاني أسماء الله الحسنى","author":"حجة اسلام ابو حامد الغزالي","publisher":"ابن حزم","publishYear":"2003","country":"لبنان","pages":"0"},{"ID":"ث83","title":"الإسلام وتحقيق الذات","author":"محمد عبد المنعم خفاجي","publisher":"دار الوفاء","publishYear":"2002","country":"الاسكندرية","pages":"0"},{"ID":"ث84","title":"تاريخ الإسلام","subtitle":"السياسي والديني والثقافي والإجتماعي","author":"حسن ابراهيم حسن","publisher":"دار الجيل","publishYear":"2001","country":"بيروت","pages":"0"},{"ID":"ث85","title":"إيضاح الرموز ومفتاح الكنوز","subtitle":"الجامع للقراءات الأربعة عشر","author":"محمد بن خليل بن أبي بكر شمس الدين بن عبد الله","publisher":"د م ج","publishYear":"1995","country":"الجزائر","pages":"0"},{"ID":"ث86","title":"الخطوبة وعلاقة الخطيبين ومهر الزوجة","subtitle":"موسوعة الزواج الإسلامي","author":"محسن النوري الموسوي","publisher":"دار الهدى","publishYear":"2007","country":"لبنان","pages":"0"},{"ID":"ث87","title":"سلسلة الدراسات الكبرى في الحياة الإسلامية","subtitle":"نظام المعاملات الإقتصادية والإجتماعية","author":"أحمد بن فريحة الغريسي","publisher":"ديوان المطبوعات الجامعية","publishYear":"2007","country":"الجزائر","pages":"0"},{"ID":"ث88","title":"السراج المنير","author":"محمد الصالح الصديق","publisher":"د.م.ج","publishYear":"1999","country":"الجزائر","pages":"0"},{"ID":"ث89","title":"إبن قيم الجوزية","subtitle":"منهجه ومروياته التاريخية في السيرة النبوية","author":"ياس خضر الحداد","publisher":"المركز القومي للبحوث","publishYear":"2001","country":"القاهرة","pages":"0"},{"ID":"ث90","title":"دليل المسلم الحزين إلى مقتضى السلوك في القرن العشرين","subtitle":"دراسات اسلامية أخرى","author":"حسين أحمد أمين","publisher":"موفم","publishYear":"1990","country":"الجزائر","pages":"0"},{"ID":"ث91","title":"النفس بين القلب والعقل في القرآن","author":"بثينة علي إبراهيم مرزوق","publisher":"مركز الاسكندرية للكت","publishYear":"2008","country":"الاسكندرية","pages":"0"},{"ID":"ث92","title":"طلائع النور","subtitle":"لوحات من السيرة النبوية العطرة","author":"عبد الملك مرتاض","publisher":"هومه","publishYear":"2007","country":"الجزائر","pages":"0"},{"ID":"ث93","title":"الإتيكيت فن السلوك الإنساني وفقا للأديان السماوية","author":"رفعت عارف الضبع","publisher":"الفكر","publishYear":"2008","country":"الأردن","pages":"0"},{"ID":"ث94","title":"الإعجاز الوجداني في القرآن","author":"عايد طه ناصف","publisher":"مؤسسة حورس الدولية","publishYear":"2008","country":"الاسكندرية","pages":"0"},{"ID":"ث95","title":"التوراة والإنجيل والقرآن","subtitle":"بين الشهادات التاريخية والمعطيات العلمية","author":"جعفر حسن عتريسي","publisher":"د.ن","publishYear":"2003","country":"لبنان","pages":"0"},{"ID":"ث96","title":"المدخل إلى دراسة الشريعة الإسلامية","author":"رابح بن غريب","publisher":"دار العلوم","publishYear":"2007","country":"عنابة","pages":"0"},{"ID":"ث97","title":"الحقوق والواجبات في الزواج المقدس","subtitle":"موسوعة الزواج الاسلامي","author":"محسن النوري الموسوي","publisher":"الهادي","publishYear":"2007","country":"لبنان","pages":"0"},{"ID":"ث98","title":"العقيدة البعثية للرئيس صدام حسين","subtitle":"دراسة في تحليل الخطاب","author":"شوتري أحمد","publisher":"طاكسيج كوم","publishYear":"2007","country":"الجزائر","pages":"0"},{"ID":"ث99","title":"رسل ثلاثة لإله واحد","author":"روجيه أرنلديز","publisher":"منشورات عويدات","publishYear":"1988","country":"لبنان","pages":"0"},{"ID":"ث100","title":"أساليب تدريس القرآن الكريم","subtitle":"التلاوة *الحفظ* التجويد","author":"محمد محمود عبد الله","publisher":"الراية","publishYear":"2007","country":"الأردن","pages":"0"},{"ID":"ث101","title":"الأخلاق في السنة النبوية","author":"هدى علي جواد الشمري","publisher":"المناهج","publishYear":"2008","country":"الأردن","pages":"0"},{"ID":"ث102","title":"الإعجاز العددي للقرآن الكريم","author":"عبد الرزاق نوفل","publisher":"opu","publishYear":"1989","country":"الجزائر","pages":"0"},{"ID":"ث103","title":"كتاب الزهد","author":"ابي عبد الله احمد","publisher":"دار الكتاب العربي","publishYear":"2004","country":"لبنان","pages":"0"},{"ID":"ث104","title":"دراسات في السيرة النبوية","author":"حسين مؤنس","publisher":"ديوان المطبوعات الجامعية","publishYear":"1990","country":"الجزائر","pages":"0"},{"ID":"ث105","title":"أعلام الموقعين عن رب العالمين","author":"للامام ابن القيم الجوزية","publisher":"دار الكتاب العربي","publishYear":"2004","country":"لبنان","pages":"0"},{"ID":"ث106","title":"الزاهر","subtitle":"في غريب ألفاظ الإمام الشافعي","author":"ابي منصور محمد ","publisher":"دار الفكر","publishYear":"1999","country":"الأردن","pages":"0"},{"ID":"ث107","title":"اقتضاء الصراط المستقيم","subtitle":"مخالفة أصحاب الجحيم","author":"ابن تيمة","publisher":"دار العلم العربي","publishYear":"1994","country":"الجزائر","pages":"0"},{"ID":"ث108","title":"النظام الصحي","subtitle":"بين الطب الإسلامي والطب الطبيعي","author":"حسين نجيب محمد","publishYear":"2002","country":"لبنان","pages":"0"},{"ID":"ث109","title":"الداء والدواء","subtitle":"للإمام إبن قيم الجوزية","author":"ابي عبد الله محمد","publisher":"دار التقوى","publishYear":"2000","country":"القاهرة","pages":"0"},{"ID":"ث110","title":"كتاب عيون الأخبار: الجزء الاول","author":"أبي محمد عبد الله بن مسلم بن قتيبة الدينوري","publisher":"المكتبة العصرية","publishYear":"2003","country":"بيروت","pages":"0"},{"ID":"ث111","title":"الفرقان","subtitle":"بين أولياء الرحمن وأولياء الشيطان","author":"شيخ الاسلام احمد بن عبد الحليم ","publisher":"دار ابن حزم","publishYear":"2003","country":"لبنان","pages":"0"},{"ID":"ث112","title":"تعليم جديد لقرن جديد","author":"مصطفى محمد رجب","publisher":"الوراق","publishYear":"2008","country":"الأردن","pages":"0"},{"ID":"ث113","title":"الإسلام في الغرب","subtitle":"قرطبة عاصمة الروح و الفكر","author":"روجيه غارودي","publisher":"دار الهادي","publishYear":"2001","country":"لبنان","pages":"0"},{"ID":"ث114","title":"اطلبوا الوطنية ولو في فرنسا","author":"أحمد بن نعمان","publisher":"دار الأمة","publishYear":"2005","country":"الجزائر","pages":"0"},{"ID":"ث115","title":"المسجد الحرام بمكة المكرمة ورسومه في الفن الإسلامي","author":"أحمد رجب محمد علي","publisher":"الدار المصرية اللبنانية","publishYear":"2000","country":"القاهرة","pages":"0"},{"ID":"ث116","title":"الأحجار الكريمة","subtitle":"دراسة تاريخية جغرافية","author":"السيد الجميلي","publisher":"مكتبة مدبولي","publishYear":"1999","country":"القاهرة","pages":"0"},{"ID":"ث117","title":"كتاب شرح تقدمه المعرفة للدخوار","author":"محمد عبده محجوب","publisher":"دار المعرفة الجامعية","publishYear":"0","country":"الاسكندرية","pages":"0"},{"ID":"ث118","title":"تاريخ أبي الفداء المسمى المختصر في أخبار البشر","author":"المؤيد عماد الدين ابي فداء اسماعيل ","publisher":"دار الكتب العلمية","publishYear":"1997","country":"لبنان","pages":"0"},{"ID":"ث119","title":"آراء وأفكار جديدة في الفن وتأصيل الهوية","author":"محمد حسين جودي","publisher":"دار صفاء","publishYear":"1999","country":"الأردن","pages":"0"},{"ID":"ث120","title":"نوادر المخطوطات","author":"عبد السلام هارون","publisher":"دار الجيل","publishYear":"1991","country":"لبنان","pages":"0"},{"ID":"ث121","title":"التراث العربي الإسلامي","subtitle":"دراسة تاريخية ومقارنة","author":"حسين محمد سليمان","publisher":"د م ج","publishYear":"1988","country":"الجزائر","pages":"0"},{"ID":"ث122","title":"اللغة والثقافة","subtitle":"دراسة أنثرولغوية لألفاظ وعلاقات القرابة في الثقافة العربية","author":"كريم زكي حسام الدين","publisher":"دار غريب","publishYear":"2001","country":"القاهرة","pages":"0"},{"ID":"ث123","title":"رحلة محمد الكبير باي الغرب الجزائري إلى الجنوب الصحراوي الجزائري 1785","author":"أحمد بن هطال التليمساني","publisher":"دار السويدي","publishYear":"2004","country":"الإمارات العربية","pages":"0"},{"ID":"ث124","title":"خمس رحلات إلى الجزائر 1904-1932","author":"محمد الخضر حسين","publisher":"دار السويدي","publishYear":"2004","country":"الإمارات العربية","pages":"0"},{"ID":"ث125","title":"المسألة الثقافية وقضايا اللسان والهوية","author":"محمد العربي ولد خليفة","publisher":"د م ج","publishYear":"2003","country":"الجزائر","pages":"0"},{"ID":"ث126","title":"المثقف والتغيير","subtitle":"قراءات في المشهد الثقافي المعاصر","author":"صلاح جرار","publisher":"دار الفارس","publishYear":"2003","country":"الأردن","pages":"0"},{"ID":"ث127","title":"محمد صلى الله عليه وسلم في نظر المفكرين الغربيين","author":"الصديق محمد الصالح","publisher":"د-م-ج","publishYear":"2005","country":"الجزائر","pages":"0"},{"ID":"ث128","title":"حزب جبهة التحرير الوطني عنوان ثورة ودليل دولة نوفمبر 1954-2004","author":"إدريس فاضلي","publisher":"د-م-ج","publishYear":"2004","country":"الجزائر","pages":"0"},{"ID":"ث129","title":"الغرب و الاسلام و الصراع الحضاري","author":"حميد حمد السعدون","publisher":"الأردن","publishYear":"2002","country":"دار وائل","pages":"0"},{"ID":"ث130","title":"شظايا و تصدعات","author":"بن قينة عمر","publisher":"دار الأمة","publishYear":"2002","country":"الجزائر","pages":"0"},{"ID":"ث131","title":"ملاك الأرض بإفريقية منذ الفتح حتى أواسط القرن الرابع للإسلام","subtitle":"مدخل لدراسة نظام إفريقية الاقتصادي السياسي","author":"أبوصوة محمود أحمد","publisher":"منشورات elga","publishYear":"2001","country":"مالطا","pages":"0"},{"ID":"ث132","title":"دموع في عيون عراقية","author":"حمادي خير الدين","publisher":"دار هومه","publishYear":"2004","country":"الجزائر","pages":"0"},{"ID":"ث133","title":"المرأة الجزائرية","subtitle":"و حركة الاصلاح النسوية العربية","author":"بوعزيز يحي","publisher":"دار الهدى","publishYear":"2001","country":"الجزائر","pages":"0"},{"ID":"ث134","title":"الهويات الوطنية و المجتمع العالي و الاعلام","subtitle":"دراسات في اجراءات تشكل الهوية في ظل الهيمنة الاعلامية العالمية","author":"سنو غسان منير، الطراح علي أحمد","publisher":"د-ن-ع","publishYear":"2002","country":"بيروت","pages":"0"},{"ID":"ث135","title":"المصلح ا لمجدد الامام ابن باديس","subtitle":"لهذا حاولوا اغتياله","author":"الصديق محمد الصالح","publisher":"د-م-ج","publishYear":"2006","country":"الجزائر","pages":"0"},{"ID":"ث136","title":"المدخل للثقافة الإسلامية","author":"المليجي يعقوب","publisher":"م.ث.ج","publishYear":"2003","country":"الإسكندرية","pages":"0"},{"ID":"ث137","title":"عبد العزيز بوتفليقة","subtitle":"بين الموهبة و القيادة رجل الأقدار و زعيم المصالحة الوطنية","author":"قوراية أحمد","publisher":"د-م-ج","publishYear":"2005","country":"الجزائر","pages":"0"},{"ID":"ث138","title":"طبقات علماء افريقية","author":"بن أبي شنب محمد","publisher":"د- م-ج","publishYear":"2006","country":"الجزائر","pages":"0"},{"ID":"ث139","title":"تلمسان عبر العصور","subtitle":"دورها في سياسة وحضارة الجزائر","author":"الطمار محمد","publisher":"د.م.ج","publishYear":"2007","country":"الجزائر","pages":"0"},{"ID":"ث140","title":"أعلام من منطقة القبائل ج1","author":"الصديق محمد الصالح","publisher":"د.م.ج","publishYear":"2007","country":"الجزائر","pages":"0"},{"ID":"ث141","title":"الروابط الثقافية بين الجزائر والخارج","author":"الطمار محمد","publisher":"د.م.ج","publishYear":"2007","country":"الجزائر","pages":"0"},{"ID":"ث142","title":"بنو يعلى لمحات من التراث اليعلاوي عادات وتقاليد","author":"بوعمامه عبد الكريم","publisher":"د.م.ج","publishYear":"2006","country":"الجزائر","pages":"0"},{"ID":"ث143","title":"حوار الحضارات والمشهد الثقافي العربي","author":"الأسد ناصر الدين وآخرون","publisher":"المؤسسة العربية للدراسات و النشر","publishYear":"2004","country":"عمان","pages":"0"},{"ID":"ث144","title":"المنتقد 1925م جريدة سياسية تهذيبية انتقادية","author":"قطش عبد الهادي","publisher":"دار الهدى","publishYear":"2005","country":"الجزائر","pages":"0"},{"ID":"ث145","title":"الرافضون عبر التاريخ ج1/ج2","author":"الصديق محمد الصالح","publisher":"د.م.ج","publishYear":"2009","country":"الجزائر","pages":"0"},{"ID":"ث146","title":"تقنيات الإتصالات عبر الأقمار الإصطناعية ج1/القطاع الفضائي ج2/القطاع الأرضي","author":"بوتيوته صديق","publisher":"د.م.ج","publishYear":"1998","country":"الجزائر","pages":"0"},{"ID":"ث147","title":"من التراث الى الاجتهاد","subtitle":"الفكر الاسلامي وقضايا الاصلاح و التجديد","author":"الميلاد زكي","publisher":"م-ث-ع","publishYear":"2004","country":"المغرب","pages":"0"},{"ID":"ث148","title":"حوارات إنسانية في الثقافة العربية","author":"زروخي اسماعيل","publisher":"دار الهدى","publishYear":"2004","country":"الجزائر","pages":"0"},{"ID":"ث149","title":"معذبو الارض","author":"فانون فرانز","publisher":"anep","publishYear":"2004","country":"الجزائر","pages":"0"},{"ID":"ث150","title":"الملل والنحل","author":"الشهرستاني ابي الفتح","publisher":"م-العربي","publishYear":"2005","country":"بيروت","pages":"0"},{"ID":"ث151","title":"هذي هي الثقافة","author":"بن نعمان احمد","publisher":"دار الامة","publishYear":"1996","country":"الجزائر","pages":"0"},{"ID":"ث152","title":"اعلام في التاريخ الاسلامي في مصر","subtitle":"افكار للتجديد ومواقف للحياة","author":"كريم سامح","publisher":"د-م-ل","publishYear":"1997","country":"القاهرة","pages":"0"},{"ID":"ث153","title":"المخطط الاعظم لتحرير القدس","subtitle":"نورالدين بن زنكي","author":"تبريزي عليا ديب","publisher":"م-ع","publishYear":"2003","country":"بيروت","pages":"0"},{"ID":"ث154","title":"رحلة محمد الزاهي الميلي من باريس إلى قسنطينة 1938","author":"حمادي عبد الله","publisher":"دار البعث","publishYear":"2004","country":"قسنطينة","pages":"0"},{"ID":"ث155","title":"من وحي البصائر","author":"الحسني محمد الهادي","publisher":"دار الأمة","publishYear":"2004","country":"الجزائر","pages":"0"},{"ID":"ث156","title":"دراسات وبحوث في الآثار والحضارة الإسلامية ك1/العمارة ك2/الفنون","author":"عثمان محمد عبد الستار","publisher":"دار الوفاء","publishYear":"2005","country":"الإسكندرية","pages":"0"},{"ID":"ث157","title":"الإعلام والمستقبل","subtitle":"أفكار ورؤى","author":"عبد القادر رزيق المخادمي","publisher":"دار هومه","publishYear":"2002","country":"الجزائر","pages":"0"},{"ID":"ث158","title":"الاقلاع عن التدخين","author":"جودي خوني","publisher":"براكتيكوم","publishYear":"2003","country":"الجزائر","pages":"0"},{"ID":"ث159","title":"نقد ثقافة الحجر و بداوة الفكر","author":"حميش بنسالم","publisher":"م.ث.العربي","publishYear":"2004","country":"المغرب","pages":"0"},{"ID":"ث160","title":"لمادا يكرهوننا","author":"ناصر بن محمد الزمل","publisher":"العبيكات","publishYear":"2004","country":"الرياض","pages":"0"},{"ID":"ث161","title":"العلاقات الدولية في الاسلام","author":"حسين عدنان السيد","publisher":"م.ج.د.ن.ت","publishYear":"2006","country":"بيروت","pages":"0"},{"ID":"ث162","title":"نقد الخطاب الاستشراقي ج1","subtitle":"الظاهرة الاستشراقية و اثرها في الدراسات الاسلامية","author":"الحاج ساسي سالم","publisher":"المدار.س","publishYear":"2002","country":"بيروت","pages":"0"},{"ID":"ث163","title":"لا تحزن","author":"القرني عائض بن عبد الله","publisher":"(د.ن)","publishYear":"0","country":"(د.م)","pages":"0"},{"ID":"ث164","title":"تفسير الأحلام","author":"بن سيرين محمد","publisher":"د.ك.ح","publishYear":"2002","country":"القاهرة","pages":"0"},{"ID":"ث165","title":"اليهود ...الاسرائيليون ...العبرانيون ...الصهاينة اساطيرهم وحقيقتهم ومصير دولتهم","author":"الفرا محمد علي","publisher":"دار مجدلاوي","publishYear":"0","country":"عمان","pages":"0"},{"ID":"ث166","title":"الاسلام وصراع الحضارات","author":"عمي محمد موسى بابا","publisher":"دار صفحات لنشر","publishYear":"2011","country":"سوريا","pages":"0"},{"ID":"ث167","title":"التاريخ الكبير لابن ابى خيثمة ج1،ج2،ج3","author":"البغدادي  احمد بن زهير بن حرب","publisher":"دار الكتب العلمية","publishYear":"2009","country":"لبنان","pages":"0"},{"ID":"ث168","title":"كتاب التاريخ الكبير ج1،ج2،ج3،ج4،ج5،ج6،ج7،ج8،ج9","author":"البخاري الحافظ ابي عبد الله محمد","publisher":"دار الكتب العلمية","publishYear":"2008","country":"بيروت","pages":"0"},{"ID":"ث169","title":"عثمان بن عفان بين الخلافة والملك","author":"هيكل محمد حسين","publisher":"دار الكتب العلمية","publishYear":"2007","country":"لبنان","pages":"0"},{"ID":"ث170","title":"مواسم العرب ج1،ج2","subtitle":"المواسم الثقافية والتجارية والدينية والطبيعية ط2","author":"حمور عرفان محمد","publisher":"دار الكتب العلمية","publishYear":"2006","country":"لبنان","pages":"0"},{"ID":"ث171","title":"الطب البديل وبعض الوصفات العلاجية في الحضارات القديمة","author":"ماهر حسن محمود محمد","publisher":"دار الوفاء لدنيا","publishYear":"2007","country":"الاسكندرية","pages":"0"},{"ID":"ث172","title":"أعلام الحضارة الإسلامية من المسلمين غير العرب","author":"درنيقة محمد احمد","publisher":"المؤسسة الحديثة","publishYear":"2011","country":"بيروت","pages":"0"},{"ID":"ث173","title":"الاوراس تاريخ وثقافة","author":"محمد صالح ونيسي","publisher":"زرياب","publishYear":"2007","country":"الجزائر","pages":"0"},{"ID":"ث174","title":"العروة الوثقى","author":"محمد سعيد غيبة","publisher":"دار المكتبي","publishYear":"2010","country":"دمشق","pages":"0"},{"ID":"ث175","title":"من ايات الله في الانسان","author":"مصطفى الاسود","publisher":"م.ح.ع","publishYear":"2010","country":"لبنان","pages":"0"},{"ID":"ث176","title":"حقوق الإنسان في الإسلام","subtitle":"دراسة مقارنة","author":"الشقيرات حسين محمود محمد","publisher":"دار الفكر","publishYear":"2010","country":"عمان","pages":"0"},{"ID":"ث177","title":"بر الوالدين بين الماضي والحاضر","author":"زايد فهد خليل","publisher":"دار يافا","publishYear":"2011","country":"عمان","pages":"0"},{"ID":"ث178","title":"أرض الميعاد","subtitle":"ثلاثة عشر كتابا غيرت أمريكا","author":"جاي باريني","publisher":"د.د.إ.ث","publishYear":"2011","country":"القاهرة","pages":"0"},{"ID":"ث179","title":"ابحاث ودراسات في النحو العربي","author":"خير الدين عيسى القاسمى","publisher":"الكتب","publishYear":"2012","country":"الاسكندرية","pages":"0"},{"ID":"ث180","title":"جماليات الفكاهة وتجليات القيم في مسرح الاطفال","subtitle":"من سلسلة مسرح الاطفال","author":"محمد فوزي مصطفى","publisher":"الوفاء","publishYear":"2012","country":"الاسكندرية","pages":"0"},{"ID":"ث181","title":"شخصية موسى النبي","author":"محمود القلينى","publisher":"ب.م","publishYear":"2011","country":"الاسكندرية","pages":"0"},{"ID":"ث182","title":"الاسرى","subtitle":"حقوقهم -واجباتهم -احكامهم","author":"ناصر عبد الله عودة عبد الجواد","publisher":"كنوز المعرفة","publishYear":"2011","country":"الاردن","pages":"0"},{"ID":"ث183","title":"الاقتصاد الرياضي","author":"حسن ياسين طعمة","publisher":"المسيرة","publishYear":"2012","country":"الاردن","pages":"0"},{"ID":"ث184","title":"التحكيم في الشريعة الاسلامية","author":"نضال جبر البلوي","publisher":"الثقافة","publishYear":"2012","country":"الاردن","pages":"0"},{"ID":"ث185","title":"تقدم العمر ببراعة","subtitle":"عمر طويل وصحة متالقة وحياة مبدعة","author":"احمد توفيق حجازي","publisher":"كنوز المعرفة","publishYear":"2012","country":"الاردن","pages":"0"},{"ID":"ث186","title":"موانع الضمان في الفقه الاسلامي","subtitle":"المال-الجنايات -الحدود","author":"محمد محمود دوجان العموش","publisher":"النقائش","publishYear":"2010","country":"الاردن","pages":"0"},{"ID":"ث187","title":"اساسيات الرياضة الحديثة","author":"محمد علي محمد","publisher":"الكتاب الحديث","publishYear":"2010","country":"القاهرة","pages":"0"},{"ID":"ث188","title":"مكتبة الزمن","author":"مروة حمدى","publisher":"الوفاء","publishYear":"2012","country":"الاسكندرية","pages":"0"},{"ID":"ث189","title":"خليلو","author":"البياتي محمود","publisher":"م،ع","publishYear":"2010","country":"بيروت","pages":"0"},{"ID":"ث190","title":"ذهب مع الريح","author":"مرغريت ميتشل","publisher":"الأهلية","publishYear":"2010","country":"عمان","pages":"0"},{"ID":"ث191","title":"وداعا أيها السلاح","author":"إيرنست همنجواي","publisher":"الأهلية","publishYear":"2010","country":"عمان","pages":"0"},{"ID":"ث192","title":"الثقافة الإسلامية و قضايا العصر","author":"نوفل أحمد","publisher":"الحامد","publishYear":"2012","country":"عمان","pages":"0"},{"ID":"ث193","title":"عز الدين المناصرة هوميروس فلسطين والاردن","author":"ابراهيم الياسين","publisher":"الراية","publishYear":"2011","country":"الاردن","pages":"0"},{"ID":"ث194","title":"ارشاد الورى باسماء مدينة خير الورى","author":"محمد شميم بن حمزة","publisher":"الكتب العلمية","publishYear":"2012","country":"بيروت","pages":"0"},{"ID":"ث195","title":"التدريس المتقدم وخبرات التعليم","subtitle":"لكيمياء المقياس الدقيق","author":"دي برادلي","publisher":"صفاء","publishYear":"2013","country":"الاردن","pages":"0"},{"ID":"ث196","title":"تكريم بالعمرة واشراقات في الحرمين","author":"محمد الصالح الصديق","publisher":"هومه","publishYear":"2012","country":"الجزائر","pages":"0"},{"ID":"ث197","title":"السنن المبين في شرح احاديث اصول الدين","author":"باي بن سيدي اعمر الكنتي الوافي","publisher":"وزارة الشؤون","publishYear":"2011","country":"تلمسان","pages":"0"},{"ID":"ث198","title":"المناهل المحمدية في شرح الصلاة الانموذجية","author":"محمد بن سليمان","publisher":"وزارة الشؤون الدينية","publishYear":"2011","country":"تلمسان","pages":"0"},{"ID":"ث199","title":"المساجد والزوايا في مدينة قسنطينة الاثرية","author":"كمال غربي","publisher":"وزارة الشؤون","publishYear":"2011","country":"تلمسان","pages":"0"},{"ID":"ث200","title":"ديوان بو عبد الله البوعبدلي","author":"الصوفي بوعبد الله البوعبدلي البطيوي","publisher":"وزارة الشؤون الدينية","publishYear":"2011","country":"تلمسان","pages":"0"},{"ID":"ث201","title":"ديوان العارف بالله ابي مدين الغوث","author":"بومدين بن عبد القادر السليماني","publisher":"وزارة الشؤون الدينية","publishYear":"2011","country":"تلمسان","pages":"0"},{"ID":"ث202","title":"ديوان محمد بن سليمان المستغانمي الندرومي","author":"محمد بن سليمان","publisher":"وزارة الشؤون الدينية","publishYear":"2011","country":"تلمسان","pages":"0"},{"ID":"ث203","title":"المعونة على مذهب عالم المدينة الامام مالك بن انس","author":"عبد الحق حميش","publisher":"وزارة الشؤون الدينية","publishYear":"2011","country":"تلمسان","pages":"0"},{"ID":"ث204","title":"لقطة العجلان","author":"حمدادو بن عمر","publisher":"وزارة الشؤون الدينية","publishYear":"2011","country":"تلمسان","pages":"0"},{"ID":"ث205","title":"عرفانية الخطاب من خلال رسائل علماء المغرب الاقصى والاوسط","author":"حمدادو بن عمر","publisher":"وزارة الشؤون الدينية","publishYear":"2011","country":"تلمسان","pages":"0"},{"ID":"ث206","title":"مدونة فقه التشريع لبناء الامارة الامام محمد بن عبد الكريم المغيلي التلمساني","subtitle":"مناقب وآثار","author":"مقدم مبروك","publisher":"وزارة الشؤون الدينية","publishYear":"2011","country":"تلمسان","pages":"0"},{"ID":"ث207","title":"تحذير العبقري من محاضرات الخضري او افادة الاخبار ببراءة الابرار","author":"محمد العربي التباني","publisher":"وزارة الشؤون الدينية","publishYear":"2011","country":"تلمسان","pages":"0"},{"ID":"ث208","title":"براءة الاشعرين من عقائد المخالفين","subtitle":"الجزء الاول -الثاني","author":"محمد العربي التبان","publisher":"وزارة الشؤون الدينية","publishYear":"2011","country":"تلمسان","pages":"0"},{"ID":"ث209","title":"نزهة الفتيان في تراجم بعض الشجعان","author":"محمد العربي التباني","publisher":"وزارة الشؤون الدينية","publishYear":"2011","country":"تلمسان","pages":"0"},{"ID":"ث210","title":"رسالة التداوي بالخمر","author":"منة الله العباس احمد بن احمد الشباسي","publisher":"وزارة الشؤون الدينية","publishYear":"2011","country":"تلمسان","pages":"0"},{"ID":"ث211","title":"الحقيقة والمجاز في الرحلة الى الحجاز","author":"العربي بن عبد الله المعسكري","publisher":"وزارة الشؤون الدينية","publishYear":"2011","country":"تلمسان","pages":"0"},{"ID":"ث212","title":"واحة الوعظ والاعتبار من كلام العزيز الغفار","subtitle":"الجزء الاول -الجزء الثاني","author":"الشيخ الهبري المجاوي","publisher":"وزارة الشؤون الدينية","publishYear":"2011","country":"تلمسان","pages":"0"},{"ID":"ث213","title":"غرامي صحيح في مصطلح الحديث","author":"علي بن عبد الرحمن بسام","publisher":"وزارة الشؤون الدينية","publishYear":"2011","country":"تلمسان","pages":"0"},{"ID":"ث214","title":"العربي بن عبد القادر بن علي المشرفي","subtitle":"حياته وآثاره ت 1895 م","author":"عبد الحق شرف","publisher":"وزارة الشؤون الدينية","publishYear":"2011","country":"تلمسان","pages":"0"},{"ID":"ث215","title":"الامام الشاعر المادح سيدي الحاج محمد بن يلس","subtitle":"الرسالة والمواقف الصوفية","author":"عبد السلام بن احمد بن محمد بن يلس","publisher":"وزارة الشؤون الدينية","publishYear":"2011","country":"تلمسان","pages":"0"},{"ID":"ث216","title":"العمارة الصحراوية التقليدية بمدينة تيندوف","author":"عبد الحق معزوز","publisher":"وزارة الشؤون الدينية","publishYear":"2011","country":"تلمسان","pages":"0"},{"ID":"ث217","title":"شواهد القبور في المغرب الاوسط بين القرنين 2-13 هـ/8-19 م","author":"عبد الحق معزوز","publisher":"وزارة الشؤون الدينية","publishYear":"2011","country":"تلمسان","pages":"0"},{"ID":"ث218","title":"الشيخ الطيب المهاجي الجزائري ت 1389-1969","subtitle":"اثار وسيرة","author":"الهواري ملاح","publisher":"وزارة الشؤون الدينية","publishYear":"2011","country":"تلمسان","pages":"0"},{"ID":"ث219","title":"الشيخ محمد بن عبد الكريم المغيلي التلمساني","subtitle":"المصلح الثائر وفكره الاصلاحي في توات والسودان الغربي الجزء الاول","author":"خير الدين شترة","publisher":"وزارة الشؤون الدينية","publishYear":"2011","country":"تلمسان","pages":"0"},{"ID":"ث220","title":"دور الشيخ عدة بن غلام الله في نشر الحكمة الصوفية وممارسة القضاء","author":"مجموعة مؤلفين","publisher":"وزارة الشؤون الدينية","publishYear":"2011","country":"تلمسان","pages":"0"},{"ID":"ث221","title":"القيم الروحية والرؤية الوطنية في الطريقة الشيخية","author":"الابيض سيدي الشيخ","publisher":"وزارة الشؤون الدينية","publishYear":"2011","country":"الجزائر","pages":"0"},{"ID":"ث222","title":"الدرر المكنونة في نوازل مازونة","author":"قندوز ماحي","publisher":"وزارة الشؤون الدينية","publishYear":"2012","country":"الجزائر","pages":"0"},{"ID":"ث223","title":"العلاقات العلمية والحضارية بين زواية وتلمسان","subtitle":"بجاية -تيزي وزو","author":"مجموعة مؤلفين","publisher":"وزارة الشؤون الدينية","publishYear":"2011","country":"تلمسان","pages":"0"},{"ID":"ث224","title":"مقتل حسناء","author":"اروى كاسو","publisher":"التكوين","publishYear":"2010","country":"سوريا","pages":"0"},{"ID":"ث225","title":"نهاية عالم الاعمال التقليدية","subtitle":"قطار الادلة","author":"رفيف محمد السيد","publisher":"مكتبة العبيكان","publishYear":"2005","country":" الرياض","pages":"0"},{"ID":"ث226","title":"الثقافة العربية في زمن العولمة","author":"حجازي احمد مجدي","publisher":"دار قباء","publishYear":"2001","country":"القاهرة","pages":"0"},{"ID":"ث227","title":"تداول ازهار القطف ونباتات الزينة","author":"امام محمد صابر نوفل","publisher":"منشاة المعارف","publishYear":"2008","country":"الاسكندرية","pages":"0"},{"ID":"ث228","title":"الأوراق التجارية الإلكترونية","subtitle":"دراسة تحليلية مقارنة","author":"الحموري ناهد فتحي","publisher":"دار الثقافة","publishYear":"2009","country":"عمان","pages":"0"},{"ID":"ث229","title":"حتى لا تمزق الكتب","author":"النعيمي مريم عبد الله","publisher":"العبيكان","publishYear":"2007","country":"الرياض","pages":"0"},{"ID":"ث230","title":"الامن و السلامة لطلبة المدارس","author":"ابراهيم شعلان","publisher":"الكتاب الحديث","publishYear":"2014","country":"القاهرة","pages":"0"},{"ID":"ث231","title":"الفقه والتاريخ في الغرب الاسلامي","subtitle":"مقاربات منهجية","author":"لخضر بولطيف","publisher":"الراية","publishYear":"2013","country":"القاهرة","pages":"0"},{"ID":"ث232","title":"تزوير التاريخ","subtitle":"في الرد على كتاب نتنياهو","author":"فايز رشيد","publisher":"الدار العربية للعلوم","publishYear":"2013","country":"لبنان","pages":"0"},{"ID":"ث233","title":"علوم الحديث","subtitle":"من النقد السند الى نقد المتن","author":"حسن حنفي","publisher":"مكتبة مدبولى","publishYear":"2009","country":"القاهرة","pages":"0"},{"ID":"ث234","title":"علوم السيرة","author":"حسن حنفي","publisher":"مكتبة مدبولي","publishYear":"2013","country":"القاهرة","pages":"0"},{"ID":"ث235","title":"الادارة الفندقية","subtitle":"نمو وتطور صناعة الفنادق في ادارة الفنادق","author":"قمحية وليد نافع","publisher":"البداية","publishYear":"2013","country":"عمان","pages":"0"},{"ID":"ث236","title":"الطب الرياضي و الاسعافات الاولية","author":"ياسين بوعيشاوي","publisher":"bibliothèque nationa","publishYear":"2013","country":"الجزائر","notecontent":"الفصل الأول: دور الطقم الطبي في تحضير الفريق ومكونات حقيبة المسعف \r\r\nالفصل الثاني: الاصابات الاكثر شيوعا في رياضة كرة القدم \r\r\nالفصل الثالث: الوقاية من الاصابات \r\r\nالفصل الرابع: ارشادات مهمة للاعبين والمسيرين والجمهور والحكام \r\r\nالفصل الخامس: الاعب يسال والدكتور يجيب \r\r\n","keywords":"الطب،الاسعافات","pages":"167"},{"ID":"ث237","title":"الرحلات الحجازية في الادب الجزائري ","author":"انساعد سميرة ","publisher":"الوكالة الافريقية للانتاج السينمائي والثقافي ","publishYear":"2011","country":"الجزائر","notecontent":"الفصل الأول: الرحلات الحجازية النثرية بالجزائر \r\r\nالفصل الثاني: دراسة في مضمون الرحلات النثرية \r\r\nالفصل الثالث: في قضايا السرد الرحلي\r\r\nالفصل الرابع: الزمان والمكان في الرحلات \r\r\nالفصل الخامس: الشخصيات واللغة في الرحلات \r\r\n","keywords":"الرحلات،الحجازية ","pages":"248"},{"ID":"ث238","title":"بذل المجهود في افحام اليهود","author":"طويلة عبد الوهاب","publisher":"دار القلم","publishYear":"1989","country":"دمشق","notecontent":"من:\r\r\nمفكرون من اليهود والنصارى اعتنقوا الاسلام \r\r\nالى :\r\r\nوعدهم بالطيران الى القدس ","keywords":"افحام ،اليهود","pages":"202"},{"ID":"ث239","title":"  حياة تيموشيجين،جنكيزخان الذي قكر في السيطرة على العالم","subtitle":"الشخصية و العصر","author":"كيتشانوف","publisher":"مركز جمعة الماجد للثقافة والتراث","publishYear":"2005","country":"دبي","notecontent":"من :\r\r\n ويلون وايسوغاي باتور\r\r\nالى :\r\r\nسمة العصر ","keywords":"جنكيز خان","pages":"405"},{"ID":"ث240","title":"احداث مثيرة وجرائم مخيفة من العالم","author":"قسم الترجمة والتعريب","publisher":"دار الكتاب الحديث","publishYear":"2008","country":"مصر","notecontent":"من\r\r\nتضع منوما لزرجها وتحاول خنقه\r\r\nالى\r\r\nاثنان الى القبر والثالث الى السجن في خلاف على الميراث","keywords":"احداث ، جرائم ، العالم","pages":"297"},{"ID":"ث241","title":"الجن المسلمون","subtitle":"من صحابة الهادي البشير محمد صلى الله عليه وسلم","author":"سامية عبد العزيز منيسى","publisher":"دار الفكر العربي","publishYear":"2013","country":"القاهرة","notecontent":"الفصل الاول : خلق الملائكة والجن والانس من كتاب الله تعالى\r\r\nالفصل الثاني : السور والايات الموجهة للانس والجن وموقف الجن منها\r\r\nالفصل الثالث : الجن في السنة النبوية الشريفة\r\r\nالفصل الرابع : ذكر صحابة رسول الله صلى الله عليه وسلم من الجن المسلمون\r\r\n","keywords":"جن ، مسلمون","pages":"270"},{"ID":"ث242","title":"داعش النشاة والتوظيف","author":"اسعد العزوني","publisher":"دار دجلة","publishYear":"2016","country":"عمان","notecontent":"من\r\r\nنشاة داعش\r\r\nالى\r\r\nالاردن وداعش","keywords":"داعش ، نشاة ، توظيف","pages":"253"},{"ID":"ث243","title":"داعش","subtitle":"تنظيم اجهزة مخابرات الدول وليس تنظيم الدولة الاسلامية ","author":"اسعد العزوني","publisher":"دار دجلة","publishYear":"2017","country":"عمان","notecontent":"من \r\r\nداعش تنظيم مخابرات الدول وليس تنظيم الدولة الاسلامية\r\r\nالى\r\r\nكش داعش","keywords":"داعش ، تنظيم ، مخابرات","pages":"157"},{"ID":"ث244","title":"في الثقافة","subtitle":"بعيدا عن اوجاع الربيع الزائف","author":"محي الدين عميمور","publisher":"دار الامة","publishYear":"2016","country":"الجزائر","keywords":"ثقافة ، ربيع","pages":"653"},{"ID":"ث245","title":"الثقافة والانسان من البدائية الى التكنولوجيا","subtitle":"دراسة في البناء الثقافي للانسان","author":"فاضل الكعبي","publisher":"دار اثراء","publishYear":"2019","country":"الاردن","notecontent":"الفصل الاول : بنية الثقافة واليات التطور التكنوانيانى\r\r\nالفصل الثاني : الثقافة والحياة الاجتماعية\r\r\nالفصل الثالث : الثقافة والسلوك\r\r\nالفصل الرابع : علم الثقافة والعلوم الانسانية\r\r\nالفصل الخامس : وعى التطور الثقافي والياته الاجتماعية\r\r\nالفصل السادس : ثقافة الانسان بين العلم و الخرافة\r\r\nالفصل السابع : الثقافة والامية الحضارية\r\r\nالفصل الثامن : مقومات الثقافة في ادراك وسائل التكنولوجيا الاتصالية\r\r\n","keywords":"ثقافة ، انسان ، تكنولوجيا","pages":"216"},{"ID":"ث246","title":"تاملات في الاشكالية الثقافية","subtitle":"الثقافة والديموقراطية","author":"محمد عبد العزيز ربيع","publisher":"دروب","publishYear":"2019","country":"عمان","notecontent":"الفصل الاول : تطور الفكرة الديموقراطية\r\r\nالفصل الثاني : ميلاد النظم الديموقراطية\r\r\nالفصل الثالث : شروط الديموقراطية\r\r\nالفصل الرابع : المال والانتخابات\r\r\nالفصل الخامس : مستقبل الديموقراطية\r\r\nالفصل السادس : الحرية والديموقراطية\r\r\nالفصل السابع : الشرعية السياسية\r\r\nالفصل الثامن : نظم الحكم الديموقراطية\r\r\nالفصل التاسع : الديموقراطية والقيادة السياسية\r\r\nالفصل العاشر : العدل والديموقراطية\r\r\nالفصل الحادي عشر: العرب والديموقراطية\r\r\nالفصل الثاني عشر : نحو نظام عربي ديمقراطي\r\r\nالفصل الثالث عشر : ملاحظات ختامية\r\r\n","keywords":"ثقافة ، اشكالية","pages":"207"},{"ID":"ث247","title":"الاستراتيجية الثقافية الفرنسية","subtitle":"او ديبلوماسية الفرنكوفونية","author":"بوقراس رقية","publisher":"مركز البحوث والدراسات حول الجزائر والعالم","publishYear":"2017","country":"الجزائر","notecontent":"الفصل الاول : الثقافة رهان النشاط الخارجي الفرنسي\r\r\nالفصل الثاني : الفرنكوفونية في الاستراتيجية الثقافية الفرنسية\r\r\nالفصل الثالث : الفرنكوفونية جيوسياسة\r\r\n","keywords":"ثقافة ، فرنسية","pages":"340"},{"ID":"ث248","title":"العمل الحر","subtitle":"تخلص من قيود الوظيفة وعش حياتك كما تحب واصل على عائد مادي مناسب","author":"ماريانا كانتويل","publisher":"مجموعة النيل العربية","publishYear":"2016","country":"القاهرة","notecontent":"الباب الاول: استعد للراحة \r\r\nالباب الثاني: كيف تصنع حياتك العملية الحرة\r\r\nالباب الثالث: فكر مثل اصحاب العمل الحر\r\r\nالباب الرابع: اصنع الثغرة التي ستفر منها الى عملك الحر","keywords":"العمل،العمل الحر","pages":"369"},{"ID":"249ث","title":"بدىء الخلق وقصص الانبياء","author":"الطاهر بن سلمة","publisher":"مطبعة اريس ","publishYear":"2018","country":"سوسة","notecontent":"من الحياة السياسية تمهيد الى حديث جرجيس بن عبد الله رضي الله تعالى عنه ","pages":"630"},{"ID":"ث250","title":"منهج اهل الحديث في الرد على المتكلمين ","subtitle":"اسسه و تطبيقاته","author":"خالد كبير علال","publisher":"مؤسسة كنوز الحكمة","publishYear":"2012","country":"الجزائر","keywords":"منهج.الحديث","pages":"93"},{"ID":"ث251","title":"عودة المواطن صالح","author":"لقمان العالم","publisher":"منشورات المكتبة الرئيسية للمطالعة العمومية ","publishYear":"2018","country":"الجزائر","keywords":"عودة ,مواطن","pages":"140"}]